{
  "vessel": "Scarabeo 8",
  "roles": [
    {
      "id": "ab",
      "title": "AB / Deck Operator",
      "subtitle": "Field execution and rounds",
      "icon": "\ud83e\uddba"
    },
    {
      "id": "stability",
      "title": "Stability Leader",
      "subtitle": "Status, overdue and priorities",
      "icon": "\ud83d\udee2"
    },
    {
      "id": "management",
      "title": "Management",
      "subtitle": "KPI and overview",
      "icon": "\ud83d\udcca"
    }
  ],
  "workOrders": [
    {
      "id": "WO-104821",
      "title": "Fire & Safety Round",
      "module": "Fire & Safety",
      "status": "Follow-up",
      "priority": "Medium",
      "progress": 70,
      "eta": "45 min"
    },
    {
      "id": "WO-104822",
      "title": "LSA / Lifeboats",
      "module": "Life Saving Appliances",
      "status": "Not Started",
      "priority": "Normal",
      "progress": 35,
      "eta": "35 min"
    },
    {
      "id": "WO-104823",
      "title": "Sling Store Follow-up",
      "module": "Sling Store",
      "status": "Defect",
      "priority": "High",
      "progress": 55,
      "eta": "30 min"
    },
    {
      "id": "WO-104824",
      "title": "Maintenance Area Status",
      "module": "Maintenance Program",
      "status": "Follow-up",
      "priority": "Medium",
      "progress": 80,
      "eta": "25 min"
    },
    {
      "id": "WO-104820",
      "title": "Daily Deck Round",
      "module": "Daily Rounds",
      "status": "Approved",
      "priority": "Normal",
      "progress": 100,
      "eta": "Complete"
    }
  ],
  "items": [
    {
      "id": "daily-wh34",
      "module": "Daily Rounds",
      "type": "Area Inspection",
      "tag": "AREA-WH-34",
      "wo": "WO-104820",
      "title": "Winch House 3/4",
      "location": "M-Deck",
      "status": "Approved",
      "priority": "Normal",
      "detail": "DROP and housekeeping inspection completed. No loose equipment observed.",
      "frequency": "Daily",
      "checks": [
        "Couplings and hoses checked",
        "Safety equipment accessible",
        "Housekeeping OK",
        "Lights and securing devices OK"
      ]
    },
    {
      "id": "daily-lb-aft",
      "module": "Daily Rounds",
      "type": "Area Inspection",
      "tag": "AREA-LB-AFT",
      "wo": "WO-104820",
      "title": "Aft Lifeboat Station",
      "location": "Tween Deck",
      "status": "Defect",
      "priority": "Medium",
      "detail": "Yellow escape marking partly slippery. Needs cleaning / anti-slip follow-up.",
      "frequency": "Daily",
      "checks": [
        "Access checked",
        "Escape route condition checked",
        "Safety equipment accessible",
        "Lighting checked"
      ]
    },
    {
      "id": "fire-fh-udk032",
      "module": "Fire & Safety",
      "type": "Fire Hydrant",
      "tag": "FH-UDK-032",
      "wo": "WO-104821",
      "title": "Fire Hydrant",
      "location": "US 32 / Outside HVAC-Compressor-BOP Room",
      "status": "Follow-up",
      "priority": "Medium",
      "detail": "Cabinet door hard to open. Needs adjustment.",
      "frequency": "1W",
      "checks": [
        "Hose present",
        "Nozzle present",
        "Hydrant wrench present",
        "Cabinet accessible"
      ]
    },
    {
      "id": "fire-w3",
      "module": "Fire & Safety",
      "type": "Water Extinguisher",
      "tag": "W-BDK-003",
      "wo": "WO-104821",
      "title": "W3 Water Extinguisher",
      "location": "B Deck Collaboration Room 2",
      "status": "Defect",
      "priority": "High",
      "detail": "Pressure gauge below green area. Replace or service extinguisher.",
      "frequency": "1M",
      "checks": [
        "Pressure gauge checked",
        "Safety pin checked",
        "Hose checked",
        "Accessibility checked"
      ]
    },
    {
      "id": "lsa-lb1",
      "module": "Life Saving Appliances",
      "type": "Lifeboat",
      "tag": "LB-001",
      "wo": "WO-104822",
      "title": "Lifeboat 1",
      "location": "Fwd Lifeboat Station Port",
      "status": "Approved",
      "priority": "Normal",
      "detail": "Visual check OK.",
      "frequency": "1W",
      "cert": "Valid until 2027-03-15",
      "checks": [
        "Access clear",
        "Covers secure",
        "No visible damage",
        "Emergency equipment accessible"
      ]
    },
    {
      "id": "lsa-mob-p",
      "module": "Life Saving Appliances",
      "type": "MOB Boat",
      "tag": "MOB-PORT",
      "wo": "WO-104822",
      "title": "MOB Boat Port",
      "location": "Port MOB Boat Station",
      "status": "Follow-up",
      "priority": "Medium",
      "detail": "One securing strap shows wear. Monitor / replace if deterioration continues.",
      "frequency": "1W",
      "cert": "Valid until 2027-02-11",
      "checks": [
        "Access clear",
        "Securing arrangement checked",
        "No visible hull damage",
        "Area free from obstruction"
      ]
    },
    {
      "id": "mp-mdeck",
      "module": "Maintenance Program",
      "type": "Area Status",
      "tag": "MP-MDECK",
      "wo": "WO-104824",
      "title": "Area Status - M-Deck",
      "location": "Main Deck General Area",
      "status": "Follow-up",
      "priority": "Low",
      "detail": "Minor housekeeping observations. No immediate safety critical issue.",
      "frequency": "Weekly",
      "checks": [
        "Walkways clear",
        "Escape routes clear",
        "No loose equipment",
        "Barriers and signs in place"
      ]
    },
    {
      "id": "sling-sca-01001",
      "module": "Sling Store",
      "type": "Lever Hoist",
      "tag": "SCA-01001",
      "wo": "WO-104823",
      "title": "Lever Hoist",
      "location": "Mud Pump Room",
      "status": "Approved",
      "priority": "Normal",
      "detail": "Loan registered. Due back within 14 days.",
      "frequency": "On Use",
      "loan": "Out",
      "loanType": "Short Term",
      "loanedTo": "Mechanical Dept.",
      "dateOut": "2026-07-08",
      "expectedReturn": "2026-07-22",
      "cert": "Valid until 2027-02-10",
      "checks": [
        "Certificate valid",
        "Chain condition OK",
        "Hook latch OK",
        "Loan location registered"
      ]
    },
    {
      "id": "sling-sca-01002",
      "module": "Sling Store",
      "type": "Chain Hoist",
      "tag": "SCA-01002",
      "wo": "WO-104823",
      "title": "Chain Hoist",
      "location": "BOP Gantry Crane",
      "status": "Defect",
      "priority": "High",
      "detail": "Overdue short term loan. Must be retrieved from field.",
      "frequency": "On Use",
      "loan": "Overdue",
      "loanType": "Short Term",
      "loanedTo": "Subsea",
      "dateOut": "2026-06-10",
      "expectedReturn": "2026-06-24",
      "cert": "Valid until 2027-02-10",
      "checks": [
        "Loan overdue",
        "Location known",
        "Retrieve from field"
      ]
    },
    {
      "id": "sling-ws-0144",
      "module": "Sling Store",
      "type": "Wire Sling",
      "tag": "WS-0144",
      "wo": "WO-104823",
      "title": "Wire Sling",
      "location": "Quarantine Shelf",
      "status": "Defect",
      "priority": "High",
      "detail": "Broken wire strands observed. Moved to quarantine shelf.",
      "frequency": "On Use",
      "loan": "Quarantine",
      "cert": "Quarantined",
      "checks": [
        "Tag readable",
        "Broken wires observed",
        "Moved to quarantine"
      ]
    },
    {
      "id": "sling-lbm-003",
      "module": "Sling Store",
      "type": "Lifting Beam",
      "tag": "LBM-003",
      "wo": "WO-104823",
      "title": "Lifting Beam",
      "location": "Beam Rack",
      "status": "Follow-up",
      "priority": "Medium",
      "detail": "Certificate expires within 30 days. Plan recertification.",
      "frequency": "Monthly",
      "loan": "In Store",
      "cert": "Expiring soon: 2026-08-01",
      "checks": [
        "Certificate checked",
        "ID readable",
        "Stored correctly",
        "Recertification planned"
      ]
    }
  ],
  "ptw": [
    {
      "id": "PTW-8821",
      "type": "Lifting Operation",
      "area": "Pipe Deck",
      "status": "Open",
      "risk": "Medium"
    },
    {
      "id": "PTW-8822",
      "type": "Working Aloft",
      "area": "Derrick Leg Stbd",
      "status": "Planned",
      "risk": "High"
    },
    {
      "id": "PTW-8823",
      "type": "Hot Work",
      "area": "Workshop",
      "status": "Closed",
      "risk": "Medium"
    }
  ],
  "toolbox": [
    {
      "topic": "Weather / wind exposure on deck",
      "status": "Completed"
    },
    {
      "topic": "Dropped object awareness",
      "status": "Completed"
    },
    {
      "topic": "Sling Store return discipline",
      "status": "Pending"
    }
  ],
  "notifications": [
    {
      "type": "AMOS",
      "text": "WO-104823 has high priority overdue equipment."
    },
    {
      "type": "Certificate",
      "text": "LBM-003 expires within 30 days."
    },
    {
      "type": "Finding",
      "text": "W3 extinguisher requires service or replacement."
    }
  ]
}